Metadata-Version: 2.1
Name: vk-spamer
Version: 1.0.2
Summary: Vk user spamer
Author: RuCodinger
Author-email: rucodinger@gmail.com
